movie_barcodes/__init__.py
movie_barcodes/__main__.py
movie_barcodes/barcode_generation.py
movie_barcodes/cli.py
movie_barcodes/color_extraction.py
movie_barcodes/utility.py
movie_barcodes/video_processing.py
movie_barcodes-0.6.3.dist-info/licenses/LICENSE
movie_barcodes-0.6.3.dist-info/METADATA
movie_barcodes-0.6.3.dist-info/WHEEL
movie_barcodes-0.6.3.dist-info/entry_points.txt
movie_barcodes-0.6.3.dist-info/top_level.txt
movie_barcodes-0.6.3.dist-info/RECORD
