Metadata-Version: 2.4
Name: movie-barcodes
Version: 0.6.3
Summary: Compress every frame of a movie in a single color barcode. Transform entire movies into stunning single-barcode visualizations. Capture the essence of cinematic storytelling through dominant color extraction from each frame.
Author-email: Clément Delteil <clement45.delteil45@gmail.com>
License:                     GNU GENERAL PUBLIC LICENSE
Project-URL: Homepage, https://github.com/Wazzabeee/movie-barcodes
Project-URL: Repository, https://github.com/Wazzabeee/movie-barcodes
Keywords: visualization,python,opencv,color extraction,data science,machine learning,movies,computer vision,multiprocessing,parallel computing,barcode,image processing,multithreading,data visualization,video processing,color barcode
Classifier: Development Status :: 3 - Alpha
Classifier: License :: OSI Approved :: GNU General Public License v2 (GPLv2)
Classifier: Natural Language :: English
Classifier: Operating System :: OS Independent
Classifier: Programming Language :: Python
Classifier: Programming Language :: Python :: 3
Classifier: Programming Language :: Python :: 3.12
Requires-Python: >=3.12
License-File: LICENSE
Requires-Dist: colorama==0.4.6
Requires-Dist: joblib==1.3.2
Requires-Dist: numpy==1.26.0
Requires-Dist: opencv-python==4.8.1.78
Requires-Dist: Pillow==10.3.0
Requires-Dist: scikit-learn==1.5.0
Requires-Dist: scipy==1.11.2
Requires-Dist: threadpoolctl==3.2.0
Requires-Dist: tqdm==4.66.3
Dynamic: license-file
